uwtools/Coordinates.file
uwtools/__init__.py
uwtools/parse_buildings.py
uwtools/parse_courses.py
uwtools/parse_schedules.py
uwtools-1.6.1.dist-info/LICENSE
uwtools-1.6.1.dist-info/METADATA
uwtools-1.6.1.dist-info/WHEEL
uwtools-1.6.1.dist-info/top_level.txt
uwtools-1.6.1.dist-info/RECORD
