Metadata-Version: 2.1
Name: uwtools
Version: 1.6.1
Summary: Easy data parsing for courses at the University of Washington
Home-page: https://upload.pypi.org/legacy/
Author: AlexEidt
Author-email: alex.eidt@outlook.com
License: MIT
Platform: UNKNOWN
Requires-Python: >=3.6
Requires-Dist: tqdm
Requires-Dist: pandas
Requires-Dist: beautifulsoup4
Requires-Dist: requests
